icalfa/__init__.py
icalfa/main.py
icalfa/assets/__init__.py
icalfa/assets/datasets/__init__.py
icalfa/assets/datasets/nl2bash_fs_1.json
icalfa/assets/datasets/nl2bash_fs_2.json
icalfa/assets/datasets/nl2bash_fs_3.json
icalfa/assets/datasets/nl2bash_fs_4.json
icalfa/assets/datasets/nl2bash_fs_5.json
icalfa/assets/docker/__init__.py
icalfa/assets/docker/docker.gitignore
icalfa/assets/docker/nl2bash1.Dockerfile
icalfa/assets/docker/nl2bash2.Dockerfile
icalfa/assets/docker/nl2bash3.Dockerfile
icalfa/assets/docker/nl2bash4.Dockerfile
icalfa/assets/docker/nl2bash5.Dockerfile
icalfa/assets/docker/setup_nl2b_fs_1.sh
icalfa/assets/docker/setup_nl2b_fs_2.sh
icalfa/assets/docker/setup_nl2b_fs_3.sh
icalfa/assets/docker/setup_nl2b_fs_4.sh
icalfa/assets/docker/setup_nl2b_fs_5.sh
icalfa/envs/__init__.py
icalfa/envs/ic_env.py
icalfa/envs/bash/__init__.py
icalfa/envs/bash/bash_env.py
icalfa/utils/__init__.py
icalfa/utils/data_loader.py
icalfa/utils/utils.py
icalfa-0.3.6.dist-info/METADATA
icalfa-0.3.6.dist-info/WHEEL
icalfa-0.3.6.dist-info/licenses/LICENSE.txt
icalfa-0.3.6.dist-info/RECORD
