Metadata-Version: 2.4
Name: icalfa
Version: 0.3.6
Summary: A fork of the InterCode benchmark used to evaluate natural language to Bash command translation.
Project-URL: Repository, https://github.com/westenfelder/InterCode-ALFA
Author-email: Finn Westenfelder <finnw@mit.edu>
License: Copyright 2025 MIT-ALFA
License-File: LICENSE.txt
Classifier: License :: OSI Approved :: MIT License
Classifier: Operating System :: OS Independent
Classifier: Programming Language :: Python :: 3
Requires-Python: >=3.10
Requires-Dist: docker
Requires-Dist: gymnasium
Requires-Dist: openai
Requires-Dist: pandas
Requires-Dist: rich
Requires-Dist: scikit-learn
